livekit/agents/__init__.py
livekit/agents/_exceptions.py
livekit/agents/inference_runner.py
livekit/agents/job.py
livekit/agents/jupyter.py
livekit/agents/log.py
livekit/agents/plugin.py
livekit/agents/py.typed
livekit/agents/types.py
livekit/agents/vad.py
livekit/agents/version.py
livekit/agents/worker.py
livekit/agents/beta/__init__.py
livekit/agents/beta/tools/send_dtmf.py
livekit/agents/beta/workflows/__init__.py
livekit/agents/beta/workflows/address.py
livekit/agents/beta/workflows/dtmf_inputs.py
livekit/agents/beta/workflows/email_address.py
livekit/agents/beta/workflows/task_group.py
livekit/agents/beta/workflows/utils.py
livekit/agents/beta/workflows/warm_transfer.py
livekit/agents/cli/__init__.py
livekit/agents/cli/cli.py
livekit/agents/cli/discover.py
livekit/agents/cli/log.py
livekit/agents/cli/proto.py
livekit/agents/cli/readchar.py
livekit/agents/cli/watcher.py
livekit/agents/inference/__init__.py
livekit/agents/inference/_utils.py
livekit/agents/inference/llm.py
livekit/agents/inference/stt.py
livekit/agents/inference/tts.py
livekit/agents/ipc/__init__.py
livekit/agents/ipc/channel.py
livekit/agents/ipc/inference_executor.py
livekit/agents/ipc/inference_proc_executor.py
livekit/agents/ipc/inference_proc_lazy_main.py
livekit/agents/ipc/job_executor.py
livekit/agents/ipc/job_proc_executor.py
livekit/agents/ipc/job_proc_lazy_main.py
livekit/agents/ipc/job_thread_executor.py
livekit/agents/ipc/log_queue.py
livekit/agents/ipc/mock_room.py
livekit/agents/ipc/proc_client.py
livekit/agents/ipc/proc_pool.py
livekit/agents/ipc/proto.py
livekit/agents/ipc/supervised_proc.py
livekit/agents/llm/__init__.py
livekit/agents/llm/_strict.py
livekit/agents/llm/chat_context.py
livekit/agents/llm/fallback_adapter.py
livekit/agents/llm/llm.py
livekit/agents/llm/mcp.py
livekit/agents/llm/realtime.py
livekit/agents/llm/remote_chat_context.py
livekit/agents/llm/tool_context.py
livekit/agents/llm/utils.py
livekit/agents/llm/_provider_format/__init__.py
livekit_agents-1.3.8.dist-info/METADATA
livekit_agents-1.3.8.dist-info/WHEEL
livekit_agents-1.3.8.dist-info/RECORD
